kb_cli/__init__.py
kb_cli/__main__.py
kb_cli-0.1.0.dist-info/METADATA
kb_cli-0.1.0.dist-info/WHEEL
kb_cli-0.1.0.dist-info/entry_points.txt
kb_cli-0.1.0.dist-info/RECORD
