Metadata-Version: 2.1
Name: kb-cli
Version: 0.1.0
Summary: 
Author: Joseph P.
Author-email: joseph.pena.q@joseph.pena.q
Requires-Python: >=3.12,<4.0
Classifier: Programming Language :: Python :: 3
Classifier: Programming Language :: Python :: 3.12
Classifier: Programming Language :: Python :: 3.13
Requires-Dist: pydantic (>=2.9.2,<2.10.0)
Requires-Dist: pyfzf (>=0.3.1,<0.4.0)
Requires-Dist: pyyaml (>=6.0.2,<6.1.0)
Requires-Dist: typer (>=0.13.0,<0.14.0)
